setup.py
MoudleSystem/__init__.py
MoudleSystem/main.py
MoudleSystem.egg-info/PKG-INFO
MoudleSystem.egg-info/SOURCES.txt
MoudleSystem.egg-info/dependency_links.txt
MoudleSystem.egg-info/requires.txt
MoudleSystem.egg-info/top_level.txt