Metadata-Version: 1.0
Name: MoudleSystem
Version: 1.1.3
Summary: 寒冬利刃的MoudleSystem&handongliren's MoudleSystem
Home-page: https://github.com/hhd2009/Python/tree/package/MoudleSystem
Author: handongliren
Author-email: 1079489986@qq.com
License: GUN Licence
Keywords: pip,MoudleSystem
Platform: any
